e80/archive.py
e80/cli.py
e80/create_project.py
e80/deploy.py
e80/dev.py
e80/init.py
e80/oauth_handler.py
e80/py.typed
e80/lib/api.py
e80/lib/constants.py
e80/lib/context.py
e80/lib/dependencies.py
e80/lib/platform.py
e80/lib/project.py
e80/lib/prompt.py
e80/lib/pyproject.py
e80/lib/sdk.py
e80/lib/user.py
e80-0.1.0a8.dist-info/METADATA
e80-0.1.0a8.dist-info/WHEEL
e80-0.1.0a8.dist-info/entry_points.txt
e80-0.1.0a8.dist-info/RECORD
