Metadata-Version: 2.4
Name: e80
Version: 0.1.0a8
Summary: CLI for interacting with 8080.io
Requires-Python: >=3.13
Requires-Dist: click>=8.2.1
Requires-Dist: e80-sdk
Requires-Dist: httpx>=0.28.1
Requires-Dist: pydantic>=2.11.7
Requires-Dist: pyyaml>=6.0.2
Requires-Dist: requests>=2.32.4
Requires-Dist: requirements-parser>=0.13.0
Requires-Dist: rich-click>=1.9.0
Requires-Dist: types-pyyaml>=6.0.12.20250516
Requires-Dist: types-requests>=2.32.4.20250611
Requires-Dist: wheel>=0.45.1
